{
  "region": "Dhaka, Bangladesh",
  "region_id": "dhaka_bangladesh",
  "season": "Spring 2024",
  "season_id": "spring_2024",
  "period": "2024-03-01 to 2024-05-31",
  "source": "NASA POWER API",
  "lat": 23.81,
  "lon": 90.41,
  "climate": "Tropical mousson",
  "weeks": [
    {
      "week": 1,
      "start_date": "2024-03-01",
      "end_date": "2024-03-07",
      "temperature_avg": 23.2,
      "temperature_max": 31.32,
      "temperature_min": 15.18,
      "precipitation_total": 2.24,
      "humidity_avg": 50.81,
      "wind_speed_avg": 1.57,
      "et0_total": 3.11
    },
    {
      "week": 2,
      "start_date": "2024-03-08",
      "end_date": "2024-03-14",
      "temperature_avg": 24.42,
      "temperature_max": 33.94,
      "temperature_min": 14.63,
      "precipitation_total": 2.36,
      "humidity_avg": 48.55,
      "wind_speed_avg": 1.57,
      "et0_total": 3.35
    },
    {
      "week": 3,
      "start_date": "2024-03-15",
      "end_date": "2024-03-21",
      "temperature_avg": 26.72,
      "temperature_max": 35.0,
      "temperature_min": 19.34,
      "precipitation_total": 25.11,
      "humidity_avg": 59.29,
      "wind_speed_avg": 1.39,
      "et0_total": 2.74
    },
    {
      "week": 4,
      "start_date": "2024-03-22",
      "end_date": "2024-03-28",
      "temperature_avg": 26.05,
      "temperature_max": 33.51,
      "temperature_min": 18.53,
      "precipitation_total": 50.76,
      "humidity_avg": 69.85,
      "wind_speed_avg": 1.57,
      "et0_total": 2.04
    },
    {
      "week": 5,
      "start_date": "2024-03-29",
      "end_date": "2024-04-04",
      "temperature_avg": 28.41,
      "temperature_max": 36.72,
      "temperature_min": 21.46,
      "precipitation_total": 60.63,
      "humidity_avg": 71.85,
      "wind_speed_avg": 2.57,
      "et0_total": 2.21
    },
    {
      "week": 6,
      "start_date": "2024-04-05",
      "end_date": "2024-04-11",
      "temperature_avg": 29.48,
      "temperature_max": 38.04,
      "temperature_min": 22.02,
      "precipitation_total": 4.75,
      "humidity_avg": 59.33,
      "wind_speed_avg": 1.78,
      "et0_total": 3.03
    },
    {
      "week": 7,
      "start_date": "2024-04-12",
      "end_date": "2024-04-18",
      "temperature_avg": 30.66,
      "temperature_max": 38.82,
      "temperature_min": 22.54,
      "precipitation_total": 15.48,
      "humidity_avg": 55.63,
      "wind_speed_avg": 1.7,
      "et0_total": 3.36
    },
    {
      "week": 8,
      "start_date": "2024-04-19",
      "end_date": "2024-04-25",
      "temperature_avg": 31.9,
      "temperature_max": 41.29,
      "temperature_min": 24.75,
      "precipitation_total": 9.08,
      "humidity_avg": 59.4,
      "wind_speed_avg": 2.88,
      "et0_total": 3.54
    },
    {
      "week": 9,
      "start_date": "2024-04-26",
      "end_date": "2024-05-02",
      "temperature_avg": 32.83,
      "temperature_max": 43.27,
      "temperature_min": 25.55,
      "precipitation_total": 12.58,
      "humidity_avg": 59.52,
      "wind_speed_avg": 2.9,
      "et0_total": 3.6
    },
    {
      "week": 10,
      "start_date": "2024-05-03",
      "end_date": "2024-05-09",
      "temperature_avg": 29.15,
      "temperature_max": 39.35,
      "temperature_min": 22.73,
      "precipitation_total": 105.82,
      "humidity_avg": 71.73,
      "wind_speed_avg": 2.22,
      "et0_total": 2.18
    },
    {
      "week": 11,
      "start_date": "2024-05-10",
      "end_date": "2024-05-16",
      "temperature_avg": 29.14,
      "temperature_max": 34.62,
      "temperature_min": 23.76,
      "precipitation_total": 51.01,
      "humidity_avg": 73.62,
      "wind_speed_avg": 1.09,
      "et0_total": 1.81
    },
    {
      "week": 12,
      "start_date": "2024-05-17",
      "end_date": "2024-05-23",
      "temperature_avg": 30.51,
      "temperature_max": 35.59,
      "temperature_min": 25.67,
      "precipitation_total": 45.59,
      "humidity_avg": 72.81,
      "wind_speed_avg": 1.29,
      "et0_total": 1.97
    }
  ]
}